trustero_api/__init__.py
trustero_api/py.typed
trustero_api/receptor_v1/__init__.py
trustero_api/receptor_v1/receptor_pb2.py
trustero_api-0.0.5.dist-info/METADATA
trustero_api-0.0.5.dist-info/WHEEL
trustero_api-0.0.5.dist-info/RECORD
