Metadata-Version: 2.1
Name: trustero_api
Version: 0.0.5
Summary: Trustero Receptor API Python Proto File Bindings
Home-page: https://pypi.org/project/python/
License: Apache-2.0
Author: Alex Gonopolskiy
Author-email: alex@trustero.com
Requires-Python: >=3.8,<4
Classifier: Development Status :: 4 - Beta
Classifier: License :: OSI Approved :: Apache Software License
Classifier: Programming Language :: Python :: 3
Classifier: Programming Language :: Python :: 3.8
Classifier: Programming Language :: Python :: 3.9
Classifier: Programming Language :: Python :: 3.10
Classifier: Programming Language :: Python :: 3.11
Classifier: Programming Language :: Python :: 3.12
Classifier: Programming Language :: Python :: 3.13
Provides-Extra: docs
Requires-Dist: importlib-metadata (>=6.0.0,<7.0.0) ; extra == "docs"
Requires-Dist: protobuf (>=5.29.0,<6.0.0)
Requires-Dist: sphinx (>=6.1.3,<7.0.0) ; extra == "docs"
Requires-Dist: sphinx-autoapi (>=2.0.1,<3.0.0) ; extra == "docs"
Requires-Dist: types-protobuf (>=5.28.3.20241030,<6.0.0.0)
Project-URL: Repository, https://github.com/trustalex/https://github.com/trustero/api
